pyCrawler/__init__.py
pyCrawler/asgi.py
pyCrawler/settings.py
pyCrawler/urls.py
pyCrawler/wsgi.py
pyCrawlerApp-0.0.1.dist-info/METADATA
pyCrawlerApp-0.0.1.dist-info/WHEEL
pyCrawlerApp-0.0.1.dist-info/top_level.txt
pyCrawlerApp-0.0.1.dist-info/RECORD
