Metadata-Version: 2.1
Name: pyCrawlerApp
Version: 0.0.1
Summary: A Crawler study project
Home-page: https://github.com/pypa/sampleproject
Author: jianluo
Author-email: jianluow@isoftstone.com
Classifier: Programming Language :: Python :: 3
Classifier: License :: OSI Approved :: MIT License
Classifier: Operating System :: OS Independent
Requires-Python: >=3.9.6
